jenkinsctl/__init__.py
jenkinsctl/cli.py
jenkinsctl/commands/__init__.py
jenkinsctl/commands/build.py
jenkinsctl/commands/config.py
jenkinsctl/commands/enable_completion.py
jenkinsctl/commands/jobs.py
jenkinsctl/commands/json.py
jenkinsctl/commands/list.py
jenkinsctl/commands/logs.py
jenkinsctl/commands/rebuild.py
jenkinsctl/configs/__init__.py
jenkinsctl/configs/config.py
jenkinsctl/configs/logging_config.py
jenkinsctl/configs/session.py
jenkinsctl/jenkins/cli_helper.py
jenkinsctl/jenkins/commons.py
jenkinsctl/jenkins/console_util.py
jenkinsctl/jenkins/job.py
jenkinsctl/jenkins/utils.py
jenkinsctl-1.0.18.dist-info/METADATA
jenkinsctl-1.0.18.dist-info/WHEEL
jenkinsctl-1.0.18.dist-info/entry_points.txt
jenkinsctl-1.0.18.dist-info/licenses/LICENSE
jenkinsctl-1.0.18.dist-info/RECORD
