Metadata-Version: 2.4
Name: jenkinsctl
Version: 1.0.18
Summary: A command-line tool to interact with Jenkins jobs 🚀
Project-URL: Documentation, https://github.com/amanshaw4511/jenkinsctl#readme
Project-URL: Homepage, https://github.com/amanshaw4511/jenkinsctl
Project-URL: Issues, https://github.com/amanshaw4511/jenkinsctl/issues
Project-URL: Repository, https://github.com/amanshaw4511/jenkinsctl
Author-email: Aman Shaw <amanshaw4511@protonmail.com>
Maintainer-email: Aman Shaw <amanshaw4511@protonmail.com>
License-Expression: GPL-3.0-or-later
License-File: LICENSE
Keywords: automation,build,ci,cli,command-line,continuous-integration,devops,jenkins,jenkins-cli,job
Classifier: Development Status :: 4 - Beta
Classifier: Environment :: Console
Classifier: Intended Audience :: Developers
Classifier: License :: OSI Approved :: GNU General Public License v3 (GPLv3)
Classifier: Operating System :: OS Independent
Classifier: Programming Language :: Python :: 3
Classifier: Programming Language :: Python :: 3.8
Classifier: Programming Language :: Python :: 3.9
Classifier: Programming Language :: Python :: 3.10
Classifier: Programming Language :: Python :: 3.11
Classifier: Topic :: Software Development :: Build Tools
Requires-Python: ~=3.8
Requires-Dist: click-completion<0.6,>=0.5.2
Requires-Dist: click<9,>=8.1.7
Requires-Dist: dynaconf<4,>=3.2.6
Requires-Dist: python-dateutil<3,>=2.9.0.post0
Requires-Dist: pyyaml<7,>=6.0.2
Requires-Dist: requests<3,>=2.32.3
Requires-Dist: rich<14,>=13.8.1
